Metadata-Version: 2.4
Name: DVR-Scan-Headless
Version: 1.8.2
Summary: Tool for finding and extracting motion events in video files (e.g. security camera footage).
Home-page: https://www.dvr-scan.com/
Author: Brandon Castellano
Author-email: brandon248@gmail.com
License: BSD 2-Clause License
Project-URL: Homepage, https://www.dvr-scan.com/
Project-URL: Repository, https://github.com/Breakthrough/DVR-Scan
Project-URL: Documentation, https://www.dvr-scan.com/docs
Project-URL: Bug Tracker, https://github.com/Breakthrough/DVR-Scan/issues
Keywords: video computer-vision analysis
Classifier: Development Status :: 5 - Production/Stable
Classifier: Environment :: Console
Classifier: Environment :: Console :: Curses
Classifier: Intended Audience :: Developers
Classifier: Intended Audience :: End Users/Desktop
Classifier: Intended Audience :: System Administrators
Classifier: License :: OSI Approved :: MIT License
Classifier: Operating System :: OS Independent
Classifier: Programming Language :: Python :: 3
Classifier: Programming Language :: Python :: 3.10
Classifier: Programming Language :: Python :: 3.11
Classifier: Programming Language :: Python :: 3.12
Classifier: Programming Language :: Python :: 3.13
Classifier: Topic :: Multimedia :: Video
Classifier: Topic :: Multimedia :: Video :: Conversion
Classifier: Topic :: Multimedia :: Video :: Non-Linear Editor
Classifier: Topic :: Utilities
Requires-Python: >=3.10
License-File: LICENSE
Requires-Dist: numpy
Requires-Dist: platformdirs
Requires-Dist: scenedetect
Requires-Dist: screeninfo
Requires-Dist: tqdm
Requires-Dist: opencv-contrib-python<4.13
Requires-Dist: pillow
Dynamic: license-file
